Cogenvdecoder/CogEnvDecoder.py
Cogenvdecoder/__init__.py
CogEnvDecoder-1.0.3.dist-info/LICENSE
CogEnvDecoder-1.0.3.dist-info/METADATA
CogEnvDecoder-1.0.3.dist-info/WHEEL
CogEnvDecoder-1.0.3.dist-info/top_level.txt
CogEnvDecoder-1.0.3.dist-info/RECORD
