Metadata-Version: 2.1
Name: CogEnvDecoder
Version: 1.0.3
Summary: For decoding observation data from Cog virtual environment
Home-page: https://github.com/DRL-CASIA/COG-sim2real-challenge
Author: Haoran Li
Author-email: lihaoran2015@ia.ac.cn
Classifier: Programming Language :: Python :: 3
Classifier: License :: OSI Approved :: MIT License
Classifier: Operating System :: OS Independent
Requires-Python: >=3.6
License-File: LICENSE
